cloudy_helpers
