Metadata-Version: 1.0
Name: cloudy-helpers
Version: 0.0.7
Summary: Cloudy helpers
Home-page: https://github.com/Stupeflix/cloudy_helpers
Author: Stupeflix
Author-email: contact@stupeflix.com
License: MIT
Platform: UNKNOWN
